phulize/__init__.py
phulize/app.py
phulize/output.py
phulize/resize.py
phulize/search.py
phulize/settings/__init__.py
phulize/settings/manager.py
phulize/settings/settings.py
phulize/utils/__init__.py
phulize/utils/bytes_conversion.py
phulize/utils/directory.py
phulize/utils/file.py
phulize/utils/folder_hierarchy.py
phulize/utils/log.py
phulize/utils/operating_system.py
phulize/utils/photo_file.py
phulize/version/__init__.py
phulize/version/progsettings.py
phulize/version/progsettings.yaml
phulize-999.dist-info/LICENSE
phulize-999.dist-info/METADATA
phulize-999.dist-info/WHEEL
phulize-999.dist-info/entry_points.txt
phulize-999.dist-info/top_level.txt
phulize-999.dist-info/RECORD
