Metadata-Version: 2.1
Name: phulize
Version: 999
Summary: A python CLI tool to resize images while conserving folder hierarchy and preserving original ones in a different folder.
Home-page: https://github.com/zaytiri/photos-bulk-resize
Author: zaytiri
Project-URL: GitHub, https://github.com/zaytiri/photos-bulk-resize
Project-URL: Changelog, https://github.com/zaytiri/photos-bulk-resize/blob/main/CHANGELOG.md
Keywords: photos,image,processing,resize,reduce,cli,folder,hierarchy,bulk
Classifier: Environment :: Console
Classifier: Intended Audience :: Developers
Classifier: License :: OSI Approved :: MIT License
Classifier: Operating System :: OS Independent
Classifier: Programming Language :: Python :: 3
Requires-Python: >=3.10.6
License-File: LICENSE
Requires-Dist: PyYAML ~=6.0
Requires-Dist: margument >=1.0.3
Requires-Dist: Pillow ~=10.2.0
